{
    "category": [
      "type",
      "_id",
      "updated_on",
      "right",
      "left",
      "last_location_id",
      "is_active",
      "title",
      "last_project_id",
      "entity"
    ],
    "budget": [
      "expanded",
      "project_id",
      "category_id",
      "end_date",
      "amount",
      "recur",
      "is_current",
      "budget_currency_id",
      "parent_budget_id",
      "entity",
      "recur_num",
      "include_credit",
      "title",
      "include_subcategories",
      "_id",
      "updated_on",
      "start_date",
      "currency_id"
    ],
    "attributes": [
      "_id",
      "default_value",
      "is_active",
      "list_values",
      "type",
      "title",
      "entity"
    ],
    "payee": [
      "is_active",
      "_id",
      "entity",
      "updated_on",
      "title",
      "last_category_id"
    ],
    "transactions": [
      "longitude",
      "from_account_id",
      "location_id",
      "note",
      "to_account_id",
      "entity",
      "datetime",
      "project_id",
      "provider",
      "template_name",
      "latitude",
      "accuracy",
      "status",
      "is_ccard_payment",
      "payee_id",
      "category_id",
      "parent_id",
      "to_amount",
      "from_amount",
      "original_currency_id",
      "original_from_amount",
      "last_recurrence",
      "is_template",
      "updated_on",
      "_id"
    ],
    "account": [
      "_id",
      "note",
      "total_limit",
      "entity",
      "total_amount",
      "last_transaction_date",
      "payment_day",
      "sort_order",
      "type",
      "updated_on",
      "is_active",
      "issuer",
      "title",
      "creation_date",
      "last_account_id",
      "last_category_id",
      "currency_id",
      "closing_day",
      "card_issuer",
      "is_include_into_totals"
    ],
    "currency": [
      "_id",
      "decimal_separator",
      "updated_on",
      "title",
      "entity",
      "decimals",
      "symbol",
      "is_active",
      "name",
      "is_default",
      "symbol_format",
      "group_separator"
    ],
    "category_attribute": [
      "entity",
      "category_id",
      "attribute_id"
    ]
}